elapi_test_pkg_xyz/VERSION
elapi_test_pkg_xyz/__init__.py
elapi_test_pkg_xyz/_exceptions.py
elapi_test_pkg_xyz/_names.py
elapi_test_pkg_xyz/api/__init__.py
elapi_test_pkg_xyz/api/api.py
elapi_test_pkg_xyz/api/endpoint.py
elapi_test_pkg_xyz/api/validators.py
elapi_test_pkg_xyz/cli/__init__.py
elapi_test_pkg_xyz/cli/__main__.py
elapi_test_pkg_xyz/cli/_plugin_handler.py
elapi_test_pkg_xyz/cli/doc.py
elapi_test_pkg_xyz/cli/elapi.py
elapi_test_pkg_xyz/configuration/__init__.py
elapi_test_pkg_xyz/configuration/_config_history.py
elapi_test_pkg_xyz/configuration/config.py
elapi_test_pkg_xyz/configuration/log_file.py
elapi_test_pkg_xyz/configuration/overridable_vars.py
elapi_test_pkg_xyz/configuration/validators.py
elapi_test_pkg_xyz/core_validators/__init__.py
elapi_test_pkg_xyz/core_validators/base.py
elapi_test_pkg_xyz/core_validators/path.py
elapi_test_pkg_xyz/loggers/__init__.py
elapi_test_pkg_xyz/loggers/base.py
elapi_test_pkg_xyz/loggers/handlers/__init__.py
elapi_test_pkg_xyz/loggers/handlers/file.py
elapi_test_pkg_xyz/loggers/handlers/stderr.py
elapi_test_pkg_xyz/path.py
elapi_test_pkg_xyz/plugins/__init__.py
elapi_test_pkg_xyz/plugins/bill_teams/__init__.py
elapi_test_pkg_xyz/plugins/bill_teams/_doc.py
elapi_test_pkg_xyz/plugins/bill_teams/bill_teams.py
elapi_test_pkg_xyz/plugins/bill_teams/cli.py
elapi_test_pkg_xyz/plugins/bill_teams/format.py
elapi_test_pkg_xyz/plugins/bill_teams/generate_table.py
elapi_test_pkg_xyz/plugins/bill_teams/invoice.py
elapi_test_pkg_xyz/plugins/bill_teams/specification.py
elapi_test_pkg_xyz/plugins/bill_teams/validators.py
elapi_test_pkg_xyz/plugins/commons/__init__.py
elapi_test_pkg_xyz/plugins/commons/cli_helpers.py
elapi_test_pkg_xyz/plugins/commons/export.py
elapi_test_pkg_xyz/plugins/commons/get_information.py
elapi_test_pkg_xyz/plugins/commons/get_location_from_headers.py
elapi_test_pkg_xyz/plugins/experiments/__init__.py
elapi_test_pkg_xyz/plugins/experiments/_doc.py
elapi_test_pkg_xyz/plugins/experiments/cli.py
elapi_test_pkg_xyz-1.3.0.dist-info/LICENSE
elapi_test_pkg_xyz-1.3.0.dist-info/METADATA
elapi_test_pkg_xyz-1.3.0.dist-info/WHEEL
elapi_test_pkg_xyz-1.3.0.dist-info/entry_points.txt
elapi_test_pkg_xyz-1.3.0.dist-info/RECORD
