Metadata-Version: 2.1
Name: elapi-test-pkg-xyz
Version: 1.3.0
Summary: elAPI is a powerful, extensible API client for eLabFTW.
Home-page: https://www.urz.uni-heidelberg.de/en/service-catalogue/software-and-applications/elabftw
License: AGPL-3.0-only
Keywords: elabftw,api
Author: Alexander Haller, Mahadi Xion
Author-email: elabftw@uni-heidelberg.de
Maintainer: Mahadi Xion
Maintainer-email: mahadi.xion@urz.uni-heidelberg.de
Requires-Python: >=3.9.0,<4.0.0
Classifier: Development Status :: 5 - Production/Stable
Classifier: Framework :: AnyIO
Classifier: Framework :: AsyncIO
Classifier: Intended Audience :: Developers
Classifier: Intended Audience :: System Administrators
Classifier: License :: OSI Approved :: GNU Affero General Public License v3
Classifier: Natural Language :: English
Classifier: Operating System :: OS Independent
Classifier: Programming Language :: Python :: 3
Classifier: Programming Language :: Python :: 3.9
Classifier: Programming Language :: Python :: 3.10
Classifier: Programming Language :: Python :: 3.11
Classifier: Topic :: Internet :: WWW/HTTP
Classifier: Topic :: Software Development :: Libraries :: Python Modules
Classifier: Topic :: System :: Systems Administration
Classifier: Topic :: Utilities
Provides-Extra: uhd-urz
Requires-Dist: dynaconf (>=3.2.0,<4.0.0)
Requires-Dist: h2 (>=4.1.0,<5.0.0)
Requires-Dist: httpx (>=0.24.1,<0.25.0)
Requires-Dist: httpx-auth (>=0.17.0,<0.18.0)
Requires-Dist: mistune (>=3.0.2,<4.0.0)
Requires-Dist: python-dateutil (>=2.8.2,<3.0.0) ; extra == "uhd-urz"
Requires-Dist: pyyaml (>=6.0.1,<7.0.0)
Requires-Dist: tenacity (>=8.2.3,<9.0.0) ; extra == "uhd-urz"
Requires-Dist: typer[all] (>=0.9.0,<0.10.0)
